zwi/__init__.py
zwi/asset_cache.py
zwi/core.py
zwi/qt_gui.py
zwi/util.py
zwi/zwi_ui_v0.ui
zwi/scripts/__init__.py
zwi/scripts/zwi.py
zwi/scripts/zwibok.py
zwi-0.3a2.dev2.dist-info/entry_points.txt
zwi-0.3a2.dev2.dist-info/LICENSE.md
zwi-0.3a2.dev2.dist-info/WHEEL
zwi-0.3a2.dev2.dist-info/METADATA
zwi-0.3a2.dev2.dist-info/RECORD
