Metadata-Version: 2.1
Name: zwi
Version: 0.3a2.dev2
Summary: Zwift data explorations.
Author-email: Damon Permezel <permezel@me.com>
Requires-Python: >=3.9
Classifier: Programming Language :: Python :: 3
Classifier: License :: OSI Approved :: MIT License
Classifier: Operating System :: OS Independent
Requires-Dist: zwift-client
Requires-Dist: PyQt5
Requires-Dist: click
Requires-Dist: keyring
Requires-Dist: bokeh
Requires-Dist: pandas
Project-URL: bug_tracker, https://github.com/permezel/zwi/issues
Project-URL: source, https://github.com/permezel/zwi
